steerage/__init__.py
steerage/datetimes.py
steerage/exceptions.py
steerage/filestorages/__init__.py
steerage/filestorages/base.py
steerage/filestorages/localfiles.py
steerage/filestorages/memdb.py
steerage/filestorages/s3.py
steerage/repositories/__init__.py
steerage/repositories/base.py
steerage/repositories/memdb.py
steerage/repositories/sessions.py
steerage/repositories/shelvedb.py
steerage/repositories/sqldb.py
steerage/types.py
steerage/uuids.py
steerage-2.0.0.dist-info/LICENSE.md
steerage-2.0.0.dist-info/METADATA
steerage-2.0.0.dist-info/WHEEL
steerage-2.0.0.dist-info/RECORD
