Metadata-Version: 2.1
Name: steerage
Version: 2.0.0
Summary: Pluggable async storage backends for Python projects
Home-page: https://github.com/eykd/steerage/
License: BSD
Author: David Eyk
Author-email: david@worldsenoughstudios.com
Requires-Python: >=3.11,<4.0
Classifier: Development Status :: 4 - Beta
Classifier: Environment :: Plugins
Classifier: License :: OSI Approved :: BSD License
Classifier: License :: Other/Proprietary License
Classifier: Programming Language :: Python :: 3
Classifier: Programming Language :: Python :: 3.11
Classifier: Programming Language :: Python :: 3.12
Classifier: Topic :: Database :: Front-Ends
Classifier: Topic :: Software Development :: Libraries :: Application Frameworks
Classifier: Topic :: Software Development :: Libraries :: Python Modules
Provides-Extra: postgresql
Provides-Extra: s3
Provides-Extra: sqlite
Requires-Dist: aioboto3 (>=12.2.0,<13.0.0) ; extra == "s3"
Requires-Dist: aiofiles (>=23.2.1,<24.0.0)
Requires-Dist: aiosqlite (>=0.19.0,<0.20.0) ; extra == "sqlite"
Requires-Dist: aiostream (>=0.5.2,<0.6.0)
Requires-Dist: asyncstdlib (>=3.12.0,<4.0.0)
Requires-Dist: convoke (>=2.0.1,<3.0.0)
Requires-Dist: funcy (>=2.0,<3.0)
Requires-Dist: httpx (>=0.26.0,<0.27.0)
Requires-Dist: pyrsistent (>=0.20.0,<0.21.0)
Requires-Dist: pytz (>=2023.3.post1,<2024.0)
Requires-Dist: sqlalchemy[asyncio] (>=2.0.25,<3.0.0) ; extra == "postgresql"
Project-URL: Documentation, https://eykd.github.io/steerage/latest/
Project-URL: Repository, https://github.com/eykd/steerage
